clustergrammer_widget2/__init__.py
clustergrammer_widget2/_version.py
clustergrammer_widget2/example.py
clustergrammer_widget2/clustergrammer/__init__.py
clustergrammer_widget2/clustergrammer/calc_clust.py
clustergrammer_widget2/clustergrammer/cat_pval.py
clustergrammer_widget2/clustergrammer/categories.py
clustergrammer_widget2/clustergrammer/data_formats.py
clustergrammer_widget2/clustergrammer/downsample_fun.py
clustergrammer_widget2/clustergrammer/enrichr_functions.py
clustergrammer_widget2/clustergrammer/export_data.py
clustergrammer_widget2/clustergrammer/iframe_web_app.py
clustergrammer_widget2/clustergrammer/initialize_net.py
clustergrammer_widget2/clustergrammer/load_data.py
clustergrammer_widget2/clustergrammer/load_vect_post.py
clustergrammer_widget2/clustergrammer/make_clust_fun.py
clustergrammer_widget2/clustergrammer/make_sim_mat.py
clustergrammer_widget2/clustergrammer/make_unique_labels.py
clustergrammer_widget2/clustergrammer/make_views.py
clustergrammer_widget2/clustergrammer/make_viz.py
clustergrammer_widget2/clustergrammer/normalize_fun.py
clustergrammer_widget2/clustergrammer/proc_df_labels.py
clustergrammer_widget2/clustergrammer/run_filter.py
clustergrammer_widget2/labextension/clustergrammer_widget2-0.4.0.tgz
clustergrammer_widget2/labextension/clustergrammer_widget2-0.4.1.tgz
clustergrammer_widget2/labextension/clustergrammer_widget2-0.4.3.tgz
clustergrammer_widget2/labextension/clustergrammer_widget2-0.4.4.tgz
clustergrammer_widget2/labextension/clustergrammer_widget2-0.4.5.tgz
clustergrammer_widget2/labextension/clustergrammer_widget2-0.5.0.tgz
clustergrammer_widget2/labextension/clustergrammer_widget2-0.5.1.tgz
clustergrammer_widget2/labextension/clustergrammer_widget2-0.6.0.tgz
clustergrammer_widget2/labextension/clustergrammer_widget2-0.6.1.tgz
clustergrammer_widget2/labextension/clustergrammer_widget2-0.6.2.tgz
clustergrammer_widget2/labextension/clustergrammer_widget2-0.6.3.tgz
clustergrammer_widget2-0.6.3.dist-info/LICENSE.txt
clustergrammer_widget2-0.6.3.dist-info/METADATA
clustergrammer_widget2-0.6.3.dist-info/RECORD
clustergrammer_widget2-0.6.3.dist-info/WHEEL
clustergrammer_widget2-0.6.3.dist-info/top_level.txt
